{
  "project_info": {
    "project_number": "1036967429772",
    "project_id": "product-3bcb0",
    "storage_bucket": "product-3bcb0.firebasestorage.app"
  },
  "client": [
    {
      "client_info": {
        "mobilesdk_app_id": "1:1036967429772:android:1f80b20c1fe5987a011da9",
        "android_client_info": {
          "package_name": "com.example.carapplication"
        }
      },
      "oauth_client": [],
      "api_key": [
        {
          "current_key": "AIzaSyBgEpNJjYvhURrWUAnDJhL3JsR0l6mFvjk"
        }
      ],
      "services": {
        "appinvite_service": {
          "other_platform_oauth_client": []
        }
      }
    }
  ],
  "configuration_version": "1"
}